vi3Translate/__init__.py
vi3Translate/translator.py
vi3Translate-1.0.0.dist-info/METADATA
vi3Translate-1.0.0.dist-info/WHEEL
vi3Translate-1.0.0.dist-info/entry_points.txt
vi3Translate-1.0.0.dist-info/top_level.txt
vi3Translate-1.0.0.dist-info/RECORD
