Metadata-Version: 2.1
Name: vi3Translate
Version: 1.0.0
Summary: A language translation utility using googletrans
Home-page: https://github.com/111722203119
Author: Vigneshwaran
Author-email: Vign22112.it@rmkec.ac.in
